LICENSE
README.md
pyproject.toml
setup.py
poshcar/Additive.py
poshcar/Cartesian.py
poshcar/Compcar.py
poshcar/Connect.py
poshcar/Disorder.py
poshcar/Distance.py
poshcar/Perovskite.py
poshcar/Seldyn.py
poshcar/Smiles.py
poshcar/__init__.py
poshcar/additive.py
poshcar/atomsub.py
poshcar/cartesian.py
poshcar/clip.py
poshcar/compcar.py
poshcar/connect.py
poshcar/cquery.py
poshcar/disorder.py
poshcar/distance.py
poshcar/elemswitch.py
poshcar/main.py
poshcar/perovskite.py
poshcar/qd.py
poshcar/seldyn.py
poshcar/slab.py
poshcar/smiles.py
poshcar/supercell.py
poshcar.egg-info/PKG-INFO
poshcar.egg-info/SOURCES.txt
poshcar.egg-info/dependency_links.txt
poshcar.egg-info/requires.txt
poshcar.egg-info/top_level.txt