Metadata-Version: 2.4
Name: poshcar
Version: 2.1.0
Summary: Crystal structure engine for VASP POSCAR files
Author-email: Andy Paul Chen <la.vache.qui.vit@gmail.com>
License: MIT License
Keywords: unit cell
Classifier: Programming Language :: Python :: 3.9
Classifier: License :: OSI Approved :: MIT License
Classifier: Operating System :: OS Independent
License-File: LICENSE
Requires-Dist: ase
Requires-Dist: pyvis
Requires-Dist: rdkit
Requires-Dist: scipy
Requires-Dist: pymatgen
Requires-Dist: chgnet
Requires-Dist: nglview
Requires-Dist: pandas
Requires-Dist: networkx
Dynamic: license-file
